library_package_porechna/BookClass.py
library_package_porechna/LibraryClass.py
library_package_porechna/ReaderClass.py
library_package_porechna/__init__.py
library_package_porechna-1.0.0.dist-info/METADATA
library_package_porechna-1.0.0.dist-info/WHEEL
library_package_porechna-1.0.0.dist-info/top_level.txt
library_package_porechna-1.0.0.dist-info/RECORD
