Metadata-Version: 2.1
Name: library-package-porechna
Version: 1.0.0
Summary: library package
Home-page: UNKNOWN
Author: porechna
Author-email: porechna@gmail.com
License: UNKNOWN
Platform: UNKNOWN
Requires-Python: >=3.6
Requires-Dist: uuid
